tornado_basic_auth.py
tornado_basic_auth-0.1.3.dist-info/DESCRIPTION.rst
tornado_basic_auth-0.1.3.dist-info/METADATA
tornado_basic_auth-0.1.3.dist-info/RECORD
tornado_basic_auth-0.1.3.dist-info/WHEEL
tornado_basic_auth-0.1.3.dist-info/metadata.json
tornado_basic_auth-0.1.3.dist-info/top_level.txt
