Metadata-Version: 2.0
Name: tornado-basic-auth
Version: 0.1.3
Summary: basic authentication for tornado
Home-page: https://github.com/zhangyangjing/tornado-basic-auth
Author: Yangjing Zhang
Author-email: zhangyangjing@gmail.com
License: Apache License 2.0
Keywords: tornado digest-auth basic-auth
Platform: UNKNOWN
Classifier: Development Status :: 4 - Beta
Classifier: Intended Audience :: Developers
Classifier: Topic :: Software Development :: Libraries
Classifier: License :: OSI Approved :: MIT License
Classifier: Programming Language :: Python
Classifier: Programming Language :: Python :: 3.5
Classifier: Programming Language :: Python :: 3.6
Classifier: Programming Language :: Python :: 3.7
Classifier: Programming Language :: Python :: Implementation
Requires-Dist: tornado (>=4.0.0)
